OHFFDRL/__init__.py
ohffdrl-0.0.2.dist-info/METADATA
ohffdrl-0.0.2.dist-info/WHEEL
ohffdrl-0.0.2.dist-info/licenses/LICENSE
ohffdrl-0.0.2.dist-info/RECORD
