Metadata-Version: 2.4
Name: OHFFDRL
Version: 0.0.2
Summary: Optimized Hierarchical Fused Fuzzy Deep Reinforcement Learning
Project-URL: source, https://github.com/arman-daliri/OHFFDRL
Author-email: Arman Daliri <daliriwork2@gmail.com>
License-Expression: MIT
License-File: LICENSE
Classifier: Intended Audience :: Science/Research
Classifier: Operating System :: OS Independent
Classifier: Programming Language :: Python
Classifier: Programming Language :: Python :: 3
Requires-Python: >=3.11
Requires-Dist: numpy
Requires-Dist: pandas
Requires-Dist: scikit-learn
Requires-Dist: tensorflow
